.gitignore
LICENSE.txt
README.rst
ez_setup.py
setup.py
django_oopviews/__init__.py
django_oopviews/base.py
django_oopviews/ctn.py
django_oopviews.egg-info/PKG-INFO
django_oopviews.egg-info/SOURCES.txt
django_oopviews.egg-info/dependency_links.txt
django_oopviews.egg-info/top_level.txt