Metadata-Version: 1.0
Name: django-oopviews
Version: 0.2.0
Summary: django-oopviews provides a simple way to write Django-views in an object-oriented manner.
Home-page: http://github.com/zerok/django-oopviews/
Author: Horst Gutmann
Author-email: zerok@zerokspot.com
License: BSD
Platform: any
Classifier: Development Status :: 4 - Beta
Classifier: Environment :: Web Environment
Classifier: Framework :: Django
Classifier: Intended Audience :: Developers
Classifier: License :: OSI Approved :: BSD License
Classifier: Operating System :: OS Independent
Classifier: Programming Language :: Python
Classifier: Topic :: Software Development :: Libraries :: Python Modules
